{"trial_id": "0052", "hyperparameters": {"space": [{"class_name": "Int", "config": {"name": "n_hidden", "default": 2, "conditions": [], "min_value": 0, "max_value": 4, "step": 1, "sampling": "linear"}}, {"class_name": "Int", "config": {"name": "n_neurons", "default": null, "conditions": [], "min_value": 8, "max_value": 64, "step": 8, "sampling": "linear"}}, {"class_name": "Choice", "config": {"name": "learning_rate", "default": 1e-05, "conditions": [], "values": [1e-05, 5e-05, 0.0001, 0.0005, 0.001, 0.0005, 0.01, 0.05], "ordered": true}}], "values": {"n_hidden": 2, "n_neurons": 56, "learning_rate": 5e-05, "tuner/epochs": 6, "tuner/initial_epoch": 0, "tuner/bracket": 2, "tuner/round": 0}}, "metrics": {"metrics": {"loss": {"direction": "min", "observations": [{"value": [0.0039389608427882195], "step": 5}]}, "mean_absolute_error": {"direction": "min", "observations": [{"value": [0.05009566992521286], "step": 5}]}, "val_loss": {"direction": "min", "observations": [{"value": [0.003997753839939833], "step": 5}]}, "val_mean_absolute_error": {"direction": "min", "observations": [{"value": [0.04999666288495064], "step": 5}]}, "lr": {"direction": "min", "observations": [{"value": [4.999999873689376e-05], "step": 5}]}}}, "score": 0.003997753839939833, "best_step": 5, "status": "COMPLETED", "message": null}